{
  "answers": [
    {
      "diagnosisId": "D.pregnancy",
      "label": "Schwangerschaft",
      "isCorrect": false
    },
    {
      "diagnosisId": "D.uterineMyoma",
      "label": "Uterusmyom",
      "isCorrect": false
    },
    {
      "diagnosisId": "D.gonococcalCervicitis",
      "label": "Gonokokken-Zervizitis",
      "isCorrect": true
    },
    {
      "diagnosisId": "D.endometrialCarcinoma",
      "label": "Endometriumkarzinom",
      "isCorrect": false
    },
    {
      "diagnosisId": "D.pelvicInflammatoryDisease",
      "label": "Pelvic Inflammatory Disease",
      "isCorrect": false
    }
  ],
  "case": "<h2>Jetziges Leiden</h2> Vorstellung der Patientin (38) bei vaginalem Ausfluss seit sechs Tagen.<br /><br />Die Patientin beschreibt den Ausfluss als gelblich.<br /><br />Zusätzlich berichtet die Patientin über eine unerwartete vaginale Blutung und vaginalen Juckreiz.<br /><br />Probleme beim Geschlechtsverkehr, Dysurie, Bauchschmerzen, Fieber, Menstruationsbeschwerden, Erbrechen und Nausea werden verneint. <h2>Systemanamnese</h2><strong>Noxen:</strong> Nichtraucherin. Alkoholkonsum 1x / Monat oder weniger, jeweils 3 - 4 Standardgetränke / Tag (Wein und Spirituosen).",
  "id": "70808c4c-ad39-4f88-a895-bc3f702ed327",
  "topic": "gynecology"
}